[{"name":"(2009 BP5)","estimated_diameter":{"meters":{"estimated_diameter_min":76.6575573531,"estimated_diameter_max":171.4115092306}},"is_potentially_hazardous_asteroid":false,"close_approach_data":[{"close_approach_date":"2009-02-03","relative_velocity":{"kilometers_per_second":"20.7520597579"},"miss_distance":{"kilometers":"7957546.5"}}]},{"name":"(2002 UK11)","estimated_diameter":{"meters":{"estimated_diameter_min":121.4940407996,"estimated_diameter_max":271.6689340891}},"is_potentially_hazardous_asteroid":true,"close_approach_data":[{"close_approach_date":"2009-02-03","relative_velocity":{"kilometers_per_second":"18.6950170838"},"miss_distance":{"kilometers":"62283048"}}]},{"name":"(2008 YV148)","estimated_diameter":{"meters":{"estimated_diameter_min":201.6299194428,"estimated_diameter_max":450.8582061718}},"is_potentially_hazardous_asteroid":false,"close_approach_data":[{"close_approach_date":"2009-02-03","relative_velocity":{"kilometers_per_second":"6.7436742234"},"miss_distance":{"kilometers":"54612928"}}]},{"name":"(2010 JE87)","estimated_diameter":{"meters":{"estimated_diameter_min":183.8886720703,"estimated_diameter_max":411.1875710413}},"is_potentially_hazardous_asteroid":true,"close_approach_data":[{"close_approach_date":"2009-02-03","relative_velocity":{"kilometers_per_second":"10.8971278249"},"miss_distance":{"kilometers":"40487152"}}]},{"name":"(2013 BS45)","estimated_diameter":{"meters":{"estimated_diameter_min":17.561231848,"estimated_diameter_max":39.2681081809}},"is_potentially_hazardous_asteroid":false,"close_approach_data":[{"close_approach_date":"2009-02-03","relative_velocity":{"kilometers_per_second":"10.2499274222"},"miss_distance":{"kilometers":"36763724"}}]},{"name":"(2014 YF)","estimated_diameter":{"meters":{"estimated_diameter_min":76.6575573531,"estimated_diameter_max":171.4115092306}},"is_potentially_hazardous_asteroid":false,"close_approach_data":[{"close_approach_date":"2009-02-03","relative_velocity":{"kilometers_per_second":"15.8646911611"},"miss_distance":{"kilometers":"54013116"}}]},{"name":"468727 (2010 JE87)","estimated_diameter":{"meters":{"estimated_diameter_min":183.8886720703,"estimated_diameter_max":411.1875710413}},"is_potentially_hazardous_asteroid":true,"close_approach_data":[{"close_approach_date":"2009-02-03","relative_velocity":{"kilometers_per_second":"10.8971241044"},"miss_distance":{"kilometers":"40487264"}}]},{"name":"470864 (2008 YV148)","estimated_diameter":{"meters":{"estimated_diameter_min":211.1324447897,"estimated_diameter_max":472.1064988055}},"is_potentially_hazardous_asteroid":false,"close_approach_data":[{"close_approach_date":"2009-02-03","relative_velocity":{"kilometers_per_second":"6.7436761716"},"miss_distance":{"kilometers":"54612960"}}]}]