[{"name":"(2008 UB95)","estimated_diameter":{"meters":{"estimated_diameter_min":30.5179232594,"estimated_diameter_max":68.2401509401}},"is_potentially_hazardous_asteroid":false,"close_approach_data":[{"close_approach_date":"1957-10-27","relative_velocity":{"kilometers_per_second":"18.4849054035"},"miss_distance":{"kilometers":"48130560"}}]},{"name":"(2009 SX1)","estimated_diameter":{"meters":{"estimated_diameter_min":461.9074602816,"estimated_diameter_max":1032.8564805039}},"is_potentially_hazardous_asteroid":false,"close_approach_data":[{"close_approach_date":"1957-10-27","relative_velocity":{"kilometers_per_second":"13.9810715499"},"miss_distance":{"kilometers":"36405508"}}]},{"name":"(2010 KU10)","estimated_diameter":{"meters":{"estimated_diameter_min":334.6223744549,"estimated_diameter_max":748.2383760735}},"is_potentially_hazardous_asteroid":false,"close_approach_data":[{"close_approach_date":"1957-10-27","relative_velocity":{"kilometers_per_second":"24.5673496233"},"miss_distance":{"kilometers":"37894404"}}]}]