[{"name":"420738 (2012 TS)","estimated_diameter":{"meters":{"estimated_diameter_min":183.8886720703,"estimated_diameter_max":411.1875710413}},"is_potentially_hazardous_asteroid":false,"close_approach_data":[{"close_approach_date":"2079-05-29","relative_velocity":{"kilometers_per_second":"8.8954394299"},"miss_distance":{"kilometers":"42814748"}}]},{"name":"(2000 SG8)","estimated_diameter":{"meters":{"estimated_diameter_min":840.5334020728,"estimated_diameter_max":1879.4898243938}},"is_potentially_hazardous_asteroid":false,"close_approach_data":[{"close_approach_date":"2079-05-29","relative_velocity":{"kilometers_per_second":"31.5473940574"},"miss_distance":{"kilometers":"64871816"}}]},{"name":"(2004 LH)","estimated_diameter":{"meters":{"estimated_diameter_min":461.9074602816,"estimated_diameter_max":1032.8564805039}},"is_potentially_hazardous_asteroid":false,"close_approach_data":[{"close_approach_date":"2079-05-29","relative_velocity":{"kilometers_per_second":"20.6877053507"},"miss_distance":{"kilometers":"28242008"}}]},{"name":"(2010 VK139)","estimated_diameter":{"meters":{"estimated_diameter_min":48.3676488219,"estimated_diameter_max":108.1533506775}},"is_potentially_hazardous_asteroid":false,"close_approach_data":[{"close_approach_date":"2079-05-29","relative_velocity":{"kilometers_per_second":"22.8664548405"},"miss_distance":{"kilometers":"69058568"}}]}]