[{"name":"88213 (2001 AF2)","estimated_diameter":{"meters":{"estimated_diameter_min":350.3926411083,"estimated_diameter_max":783.5017643338}},"is_potentially_hazardous_asteroid":false,"close_approach_data":[{"close_approach_date":"1937-03-08","relative_velocity":{"kilometers_per_second":"27.2168113657"},"miss_distance":{"kilometers":"56500772"}}]},{"name":"(2010 RX30)","estimated_diameter":{"meters":{"estimated_diameter_min":10.1054341542,"estimated_diameter_max":22.5964377109}},"is_potentially_hazardous_asteroid":false,"close_approach_data":[{"close_approach_date":"1937-03-08","relative_velocity":{"kilometers_per_second":"16.6367503091"},"miss_distance":{"kilometers":"68214264"}}]}]