[{"name":"(2002 QQ40)","estimated_diameter":{"meters":{"estimated_diameter_min":139.4938229344,"estimated_diameter_max":311.9176705226}},"is_potentially_hazardous_asteroid":true,"close_approach_data":[{"close_approach_date":"2093-09-19","relative_velocity":{"kilometers_per_second":"14.904240574"},"miss_distance":{"kilometers":"12741654"}}]},{"name":"(2006 UA)","estimated_diameter":{"meters":{"estimated_diameter_min":265.8,"estimated_diameter_max":594.3468684194}},"is_potentially_hazardous_asteroid":false,"close_approach_data":[{"close_approach_date":"2093-09-19","relative_velocity":{"kilometers_per_second":"10.7627949209"},"miss_distance":{"kilometers":"29444658"}}]},{"name":"(2013 LR6)","estimated_diameter":{"meters":{"estimated_diameter_min":7.3207398935,"estimated_diameter_max":16.3696720474}},"is_potentially_hazardous_asteroid":false,"close_approach_data":[{"close_approach_date":"2093-09-19","relative_velocity":{"kilometers_per_second":"21.7773758987"},"miss_distance":{"kilometers":"61772692"}}]},{"name":"(2014 EH45)","estimated_diameter":{"meters":{"estimated_diameter_min":73.2073989347,"estimated_diameter_max":163.696720474}},"is_potentially_hazardous_asteroid":false,"close_approach_data":[{"close_approach_date":"2093-09-19","relative_velocity":{"kilometers_per_second":"11.0278715098"},"miss_distance":{"kilometers":"27357706"}}]},{"name":"(2014 SF304)","estimated_diameter":{"meters":{"estimated_diameter_min":9.216265485,"estimated_diameter_max":20.6081961232}},"is_potentially_hazardous_asteroid":false,"close_approach_data":[{"close_approach_date":"2093-09-19","relative_velocity":{"kilometers_per_second":"12.0154120299"},"miss_distance":{"kilometers":"26636412"}}]}]