[{"name":"(1994 JX)","estimated_diameter":{"meters":{"estimated_diameter_min":1010.5434154201,"estimated_diameter_max":2259.643771094}},"is_potentially_hazardous_asteroid":false,"close_approach_data":[{"close_approach_date":"1953-05-25","relative_velocity":{"kilometers_per_second":"18.9264411607"},"miss_distance":{"kilometers":"55961532"}}]},{"name":"488450 (1994 JX)","estimated_diameter":{"meters":{"estimated_diameter_min":1010.5434154201,"estimated_diameter_max":2259.643771094}},"is_potentially_hazardous_asteroid":false,"close_approach_data":[{"close_approach_date":"1953-05-25","relative_velocity":{"kilometers_per_second":"18.9264605597"},"miss_distance":{"kilometers":"55961932"}}]}]