[{"name":"250680 (2005 QC5)","estimated_diameter":{"meters":{"estimated_diameter_min":291.4439045349,"estimated_diameter_max":651.6883821679}},"is_potentially_hazardous_asteroid":true,"close_approach_data":[{"close_approach_date":"2096-07-23","relative_velocity":{"kilometers_per_second":"24.6946810733"},"miss_distance":{"kilometers":"72086336"}}]},{"name":"(2013 KJ6)","estimated_diameter":{"meters":{"estimated_diameter_min":278.3267680719,"estimated_diameter_max":622.3575733667}},"is_potentially_hazardous_asteroid":false,"close_approach_data":[{"close_approach_date":"2096-07-23","relative_velocity":{"kilometers_per_second":"14.1285698773"},"miss_distance":{"kilometers":"65981624"}}]},{"name":"(2013 XG22)","estimated_diameter":{"meters":{"estimated_diameter_min":231.5021222103,"estimated_diameter_max":517.6544821978}},"is_potentially_hazardous_asteroid":false,"close_approach_data":[{"close_approach_date":"2096-07-23","relative_velocity":{"kilometers_per_second":"16.2212705595"},"miss_distance":{"kilometers":"63733692"}}]},{"name":"(2017 NS5)","estimated_diameter":{"meters":{"estimated_diameter_min":187.825682933,"estimated_diameter_max":419.9909949586}},"is_potentially_hazardous_asteroid":true,"close_approach_data":[{"close_approach_date":"2096-07-23","relative_velocity":{"kilometers_per_second":"21.09984747"},"miss_distance":{"kilometers":"39414504"}}]}]