[{"name":"385605 (2005 EJ225)","estimated_diameter":{"meters":{"estimated_diameter_min":421.2646105562,"estimated_diameter_max":941.9763057186}},"is_potentially_hazardous_asteroid":true,"close_approach_data":[{"close_approach_date":"1965-03-24","relative_velocity":{"kilometers_per_second":"22.684108281"},"miss_distance":{"kilometers":"33300202"}}]},{"name":"(2010 VC72)","estimated_diameter":{"meters":{"estimated_diameter_min":66.7659413495,"estimated_diameter_max":149.2931834393}},"is_potentially_hazardous_asteroid":false,"close_approach_data":[{"close_approach_date":"1965-03-24","relative_velocity":{"kilometers_per_second":"14.3180393387"},"miss_distance":{"kilometers":"56437396"}}]}]