[{"name":"(2013 JV17)","estimated_diameter":{"meters":{"estimated_diameter_min":7.6657557353,"estimated_diameter_max":17.1411509231}},"is_potentially_hazardous_asteroid":false,"close_approach_data":[{"close_approach_date":"2069-12-05","relative_velocity":{"kilometers_per_second":"15.1729304691"},"miss_distance":{"kilometers":"41988756"}}]},{"name":"(2015 BW510)","estimated_diameter":{"meters":{"estimated_diameter_min":183.8886720703,"estimated_diameter_max":411.1875710413}},"is_potentially_hazardous_asteroid":false,"close_approach_data":[{"close_approach_date":"2069-12-05","relative_velocity":{"kilometers_per_second":"12.9228924956"},"miss_distance":{"kilometers":"58657760"}}]},{"name":"(2016 AV65)","estimated_diameter":{"meters":{"estimated_diameter_min":26.58,"estimated_diameter_max":59.4346868419}},"is_potentially_hazardous_asteroid":false,"close_approach_data":[{"close_approach_date":"2069-12-05","relative_velocity":{"kilometers_per_second":"8.8669686402"},"miss_distance":{"kilometers":"25214276"}}]},{"name":"(2012 EC)","estimated_diameter":{"meters":{"estimated_diameter_min":55.5334911581,"estimated_diameter_max":124.1766612574}},"is_potentially_hazardous_asteroid":false,"close_approach_data":[{"close_approach_date":"2069-12-05","relative_velocity":{"kilometers_per_second":"5.7111227854"},"miss_distance":{"kilometers":"45759508"}}]}]