[{"name":"357028 (2000 EJ26)","estimated_diameter":{"meters":{"estimated_diameter_min":350.3926411083,"estimated_diameter_max":783.5017643338}},"is_potentially_hazardous_asteroid":true,"close_approach_data":[{"close_approach_date":"2096-03-21","relative_velocity":{"kilometers_per_second":"28.3516347731"},"miss_distance":{"kilometers":"40085516"}}]},{"name":"(1998 WB2)","estimated_diameter":{"meters":{"estimated_diameter_min":116.0259082094,"estimated_diameter_max":259.4418179074}},"is_potentially_hazardous_asteroid":true,"close_approach_data":[{"close_approach_date":"2096-03-21","relative_velocity":{"kilometers_per_second":"11.2395611978"},"miss_distance":{"kilometers":"12273294"}}]},{"name":"(2000 CE59)","estimated_diameter":{"meters":{"estimated_diameter_min":221.0828103591,"estimated_diameter_max":494.3561926196}},"is_potentially_hazardous_asteroid":true,"close_approach_data":[{"close_approach_date":"2096-03-21","relative_velocity":{"kilometers_per_second":"17.3093880848"},"miss_distance":{"kilometers":"67467072"}}]},{"name":"(2009 FY10)","estimated_diameter":{"meters":{"estimated_diameter_min":253.8370293645,"estimated_diameter_max":567.5968528656}},"is_potentially_hazardous_asteroid":false,"close_approach_data":[{"close_approach_date":"2096-03-21","relative_velocity":{"kilometers_per_second":"21.2903719485"},"miss_distance":{"kilometers":"74455416"}}]},{"name":"(2014 UW33)","estimated_diameter":{"meters":{"estimated_diameter_min":73.2073989347,"estimated_diameter_max":163.696720474}},"is_potentially_hazardous_asteroid":false,"close_approach_data":[{"close_approach_date":"2096-03-21","relative_velocity":{"kilometers_per_second":"17.6757854872"},"miss_distance":{"kilometers":"69648952"}}]},{"name":"483422 (2000 CE59)","estimated_diameter":{"meters":{"estimated_diameter_min":211.1324447897,"estimated_diameter_max":472.1064988055}},"is_potentially_hazardous_asteroid":true,"close_approach_data":[{"close_approach_date":"2096-03-21","relative_velocity":{"kilometers_per_second":"17.309386195"},"miss_distance":{"kilometers":"67467056"}}]},{"name":"(2017 FO127)","estimated_diameter":{"meters":{"estimated_diameter_min":10.9333934415,"estimated_diameter_max":24.44781096}},"is_potentially_hazardous_asteroid":false,"close_approach_data":[{"close_approach_date":"2096-03-21","relative_velocity":{"kilometers_per_second":"15.7177332074"},"miss_distance":{"kilometers":"45142692"}}]}]