[{"name":"(2004 RY164)","estimated_diameter":{"meters":{"estimated_diameter_min":192.5550781879,"estimated_diameter_max":430.566244241}},"is_potentially_hazardous_asteroid":false,"close_approach_data":[{"close_approach_date":"2004-09-27","relative_velocity":{"kilometers_per_second":"18.8268283161"},"miss_distance":{"kilometers":"46011400"}}]},{"name":"255071 (2005 UH6)","estimated_diameter":{"meters":{"estimated_diameter_min":581.5070396458,"estimated_diameter_max":1300.2892700427}},"is_potentially_hazardous_asteroid":true,"close_approach_data":[{"close_approach_date":"2004-09-27","relative_velocity":{"kilometers_per_second":"32.6876553401"},"miss_distance":{"kilometers":"58594816"}}]},{"name":"326388 (2001 QD96)","estimated_diameter":{"meters":{"estimated_diameter_min":608.9126221057,"estimated_diameter_max":1361.5700153859}},"is_potentially_hazardous_asteroid":false,"close_approach_data":[{"close_approach_date":"2004-09-27","relative_velocity":{"kilometers_per_second":"11.4464269731"},"miss_distance":{"kilometers":"58717052"}}]},{"name":"(2005 XY4)","estimated_diameter":{"meters":{"estimated_diameter_min":53.0340723319,"estimated_diameter_max":118.5877908577}},"is_potentially_hazardous_asteroid":false,"close_approach_data":[{"close_approach_date":"2004-09-27","relative_velocity":{"kilometers_per_second":"17.4153095964"},"miss_distance":{"kilometers":"71363728"}}]},{"name":"(2008 GM2)","estimated_diameter":{"meters":{"estimated_diameter_min":5.8150703965,"estimated_diameter_max":13.0028927004}},"is_potentially_hazardous_asteroid":false,"close_approach_data":[{"close_approach_date":"2004-09-27","relative_velocity":{"kilometers_per_second":"9.6106093416"},"miss_distance":{"kilometers":"25855816"}}]},{"name":"(2017 QS17)","estimated_diameter":{"meters":{"estimated_diameter_min":299.8851611343,"estimated_diameter_max":670.5636057398}},"is_potentially_hazardous_asteroid":false,"close_approach_data":[{"close_approach_date":"2004-09-27","relative_velocity":{"kilometers_per_second":"16.5465479764"},"miss_distance":{"kilometers":"32285878"}}]},{"name":"(2017 SS32)","estimated_diameter":{"meters":{"estimated_diameter_min":71.9043188571,"estimated_diameter_max":160.7829448404}},"is_potentially_hazardous_asteroid":false,"close_approach_data":[{"close_approach_date":"2004-09-27","relative_velocity":{"kilometers_per_second":"11.550096103"},"miss_distance":{"kilometers":"30568898"}}]}]