[{"name":"310560 (2001 QL142)","estimated_diameter":{"meters":{"estimated_diameter_min":732.0739893473,"estimated_diameter_max":1636.96720474}},"is_potentially_hazardous_asteroid":true,"close_approach_data":[{"close_approach_date":"2055-01-19","relative_velocity":{"kilometers_per_second":"31.2976820539"},"miss_distance":{"kilometers":"67287056"}}]},{"name":"(2002 BG)","estimated_diameter":{"meters":{"estimated_diameter_min":211.1324447897,"estimated_diameter_max":472.1064988055}},"is_potentially_hazardous_asteroid":false,"close_approach_data":[{"close_approach_date":"2055-01-19","relative_velocity":{"kilometers_per_second":"12.2251039001"},"miss_distance":{"kilometers":"21239774"}}]},{"name":"(2009 WO106)","estimated_diameter":{"meters":{"estimated_diameter_min":402.3045798343,"estimated_diameter_max":899.5803881691}},"is_potentially_hazardous_asteroid":true,"close_approach_data":[{"close_approach_date":"2055-01-19","relative_velocity":{"kilometers_per_second":"16.0536085205"},"miss_distance":{"kilometers":"21298324"}}]},{"name":"494975 (2009 WO106)","estimated_diameter":{"meters":{"estimated_diameter_min":402.3045798343,"estimated_diameter_max":899.5803881691}},"is_potentially_hazardous_asteroid":true,"close_approach_data":[{"close_approach_date":"2055-01-19","relative_velocity":{"kilometers_per_second":"16.0535296787"},"miss_distance":{"kilometers":"21297906"}}]},{"name":"(2018 AW)","estimated_diameter":{"meters":{"estimated_diameter_min":332.1658469787,"estimated_diameter_max":742.7454136483}},"is_potentially_hazardous_asteroid":false,"close_approach_data":[{"close_approach_date":"2055-01-19","relative_velocity":{"kilometers_per_second":"33.8662975388"},"miss_distance":{"kilometers":"15533914"}}]}]