[{"name":"(2011 EW29)","estimated_diameter":{"meters":{"estimated_diameter_min":183.8886720703,"estimated_diameter_max":411.1875710413}},"is_potentially_hazardous_asteroid":false,"close_approach_data":[{"close_approach_date":"2036-04-07","relative_velocity":{"kilometers_per_second":"12.3633735148"},"miss_distance":{"kilometers":"45738416"}}]},{"name":"(2011 PF2)","estimated_diameter":{"meters":{"estimated_diameter_min":101.054341542,"estimated_diameter_max":225.9643771094}},"is_potentially_hazardous_asteroid":false,"close_approach_data":[{"close_approach_date":"2036-04-07","relative_velocity":{"kilometers_per_second":"12.7132780111"},"miss_distance":{"kilometers":"61500104"}}]}]