[{"name":"152952 (2000 GC2)","estimated_diameter":{"meters":{"estimated_diameter_min":802.7031672829,"estimated_diameter_max":1794.8988477988}},"is_potentially_hazardous_asteroid":false,"close_approach_data":[{"close_approach_date":"1966-09-18","relative_velocity":{"kilometers_per_second":"26.7465426212"},"miss_distance":{"kilometers":"41792116"}}]},{"name":"(2012 SR56)","estimated_diameter":{"meters":{"estimated_diameter_min":36.6906137531,"estimated_diameter_max":82.0427064882}},"is_potentially_hazardous_asteroid":false,"close_approach_data":[{"close_approach_date":"1966-09-18","relative_velocity":{"kilometers_per_second":"10.4311486963"},"miss_distance":{"kilometers":"1074403.25"}}]},{"name":"(2016 TZ93)","estimated_diameter":{"meters":{"estimated_diameter_min":46.1907460282,"estimated_diameter_max":103.2856480504}},"is_potentially_hazardous_asteroid":false,"close_approach_data":[{"close_approach_date":"1966-09-18","relative_velocity":{"kilometers_per_second":"11.5924804801"},"miss_distance":{"kilometers":"13127265"}}]},{"name":"(2016 TX55)","estimated_diameter":{"meters":{"estimated_diameter_min":265.8,"estimated_diameter_max":594.3468684194}},"is_potentially_hazardous_asteroid":false,"close_approach_data":[{"close_approach_date":"1966-09-18","relative_velocity":{"kilometers_per_second":"15.3783346161"},"miss_distance":{"kilometers":"55155544"}}]},{"name":"(2017 RX2)","estimated_diameter":{"meters":{"estimated_diameter_min":13.6130354855,"estimated_diameter_max":30.4396727256}},"is_potentially_hazardous_asteroid":false,"close_approach_data":[{"close_approach_date":"1966-09-18","relative_velocity":{"kilometers_per_second":"12.2580350739"},"miss_distance":{"kilometers":"4138099.5"}}]}]