[{"name":"433939 (1995 DW1)","estimated_diameter":{"meters":{"estimated_diameter_min":152.9519353442,"estimated_diameter_max":342.0109247198}},"is_potentially_hazardous_asteroid":false,"close_approach_data":[{"close_approach_date":"2156-11-28","relative_velocity":{"kilometers_per_second":"18.0660769935"},"miss_distance":{"kilometers":"40613316"}}]},{"name":"(1994 XL1)","estimated_diameter":{"meters":{"estimated_diameter_min":175.6123184804,"estimated_diameter_max":392.6810818086}},"is_potentially_hazardous_asteroid":true,"close_approach_data":[{"close_approach_date":"2156-11-28","relative_velocity":{"kilometers_per_second":"25.1671698764"},"miss_distance":{"kilometers":"60730828"}}]},{"name":"(2001 JW1)","estimated_diameter":{"meters":{"estimated_diameter_min":242.4124811008,"estimated_diameter_max":542.0507863358}},"is_potentially_hazardous_asteroid":false,"close_approach_data":[{"close_approach_date":"2156-11-28","relative_velocity":{"kilometers_per_second":"18.7147916301"},"miss_distance":{"kilometers":"41375280"}}]},{"name":"(2005 HN3)","estimated_diameter":{"meters":{"estimated_diameter_min":152.9519353442,"estimated_diameter_max":342.0109247198}},"is_potentially_hazardous_asteroid":false,"close_approach_data":[{"close_approach_date":"2156-11-28","relative_velocity":{"kilometers_per_second":"16.307884257"},"miss_distance":{"kilometers":"62657620"}}]},{"name":"(2005 WA1)","estimated_diameter":{"meters":{"estimated_diameter_min":127.2198785394,"estimated_diameter_max":284.4722965033}},"is_potentially_hazardous_asteroid":true,"close_approach_data":[{"close_approach_date":"2156-11-28","relative_velocity":{"kilometers_per_second":"17.1973271334"},"miss_distance":{"kilometers":"15569443"}}]},{"name":"(2010 XJ3)","estimated_diameter":{"meters":{"estimated_diameter_min":152.9519353442,"estimated_diameter_max":342.0109247198}},"is_potentially_hazardous_asteroid":false,"close_approach_data":[{"close_approach_date":"2156-11-28","relative_velocity":{"kilometers_per_second":"18.181731228"},"miss_distance":{"kilometers":"23929276"}}]},{"name":"480808 (1994 XL1)","estimated_diameter":{"meters":{"estimated_diameter_min":175.6123184804,"estimated_diameter_max":392.6810818086}},"is_potentially_hazardous_asteroid":true,"close_approach_data":[{"close_approach_date":"2156-11-28","relative_velocity":{"kilometers_per_second":"25.1668537686"},"miss_distance":{"kilometers":"60729540"}}]}]