[{"name":"208023 (1999 AQ10)","estimated_diameter":{"meters":{"estimated_diameter_min":221.0828103591,"estimated_diameter_max":494.3561926196}},"is_potentially_hazardous_asteroid":true,"close_approach_data":[{"close_approach_date":"1958-10-22","relative_velocity":{"kilometers_per_second":"14.511455541"},"miss_distance":{"kilometers":"36733024"}}]},{"name":"(2016 HJ19)","estimated_diameter":{"meters":{"estimated_diameter_min":192.5550781879,"estimated_diameter_max":430.566244241}},"is_potentially_hazardous_asteroid":false,"close_approach_data":[{"close_approach_date":"1958-10-22","relative_velocity":{"kilometers_per_second":"24.2682562371"},"miss_distance":{"kilometers":"46202324"}}]},{"name":"(2017 XO2)","estimated_diameter":{"meters":{"estimated_diameter_min":87.1675775121,"estimated_diameter_max":194.912628751}},"is_potentially_hazardous_asteroid":false,"close_approach_data":[{"close_approach_date":"1958-10-22","relative_velocity":{"kilometers_per_second":"9.6039330439"},"miss_distance":{"kilometers":"28086604"}}]}]