[{"name":"175114 (2004 QQ)","estimated_diameter":{"meters":{"estimated_diameter_min":1272.1987853936,"estimated_diameter_max":2844.7229650327}},"is_potentially_hazardous_asteroid":false,"close_approach_data":[{"close_approach_date":"1916-09-25","relative_velocity":{"kilometers_per_second":"13.2126112256"},"miss_distance":{"kilometers":"25841726"}}]},{"name":"311554 (2006 BQ147)","estimated_diameter":{"meters":{"estimated_diameter_min":483.6764882185,"estimated_diameter_max":1081.533506775}},"is_potentially_hazardous_asteroid":false,"close_approach_data":[{"close_approach_date":"1916-09-25","relative_velocity":{"kilometers_per_second":"20.8367987233"},"miss_distance":{"kilometers":"70522280"}}]},{"name":"(2011 HJ7)","estimated_diameter":{"meters":{"estimated_diameter_min":96.5061469579,"estimated_diameter_max":215.7943048444}},"is_potentially_hazardous_asteroid":false,"close_approach_data":[{"close_approach_date":"1916-09-25","relative_velocity":{"kilometers_per_second":"15.2734627348"},"miss_distance":{"kilometers":"54799576"}}]}]