[{"name":"184990 (2006 KE89)","estimated_diameter":{"meters":{"estimated_diameter_min":1394.9382293439,"estimated_diameter_max":3119.1767052261}},"is_potentially_hazardous_asteroid":false,"close_approach_data":[{"close_approach_date":"2180-06-20","relative_velocity":{"kilometers_per_second":"27.9009923924"},"miss_distance":{"kilometers":"49778596"}}]},{"name":"(2010 GV147)","estimated_diameter":{"meters":{"estimated_diameter_min":530.3407233187,"estimated_diameter_max":1185.8779085771}},"is_potentially_hazardous_asteroid":false,"close_approach_data":[{"close_approach_date":"2180-06-20","relative_velocity":{"kilometers_per_second":"35.8631690254"},"miss_distance":{"kilometers":"55719568"}}]}]