[{"name":"(2014 PB58)","estimated_diameter":{"meters":{"estimated_diameter_min":175.6123184804,"estimated_diameter_max":392.6810818086}},"is_potentially_hazardous_asteroid":false,"close_approach_data":[{"close_approach_date":"2091-01-22","relative_velocity":{"kilometers_per_second":"26.580017364"},"miss_distance":{"kilometers":"30145632"}}]},{"name":"(2015 DC1)","estimated_diameter":{"meters":{"estimated_diameter_min":29.1443904535,"estimated_diameter_max":65.1688382168}},"is_potentially_hazardous_asteroid":false,"close_approach_data":[{"close_approach_date":"2091-01-22","relative_velocity":{"kilometers_per_second":"11.6578822084"},"miss_distance":{"kilometers":"45610756"}}]},{"name":"(2017 QB2)","estimated_diameter":{"meters":{"estimated_diameter_min":34.115754192,"estimated_diameter_max":76.285145477}},"is_potentially_hazardous_asteroid":false,"close_approach_data":[{"close_approach_date":"2091-01-22","relative_velocity":{"kilometers_per_second":"6.4653720977"},"miss_distance":{"kilometers":"17855930"}}]},{"name":"(2017 YJ7)","estimated_diameter":{"meters":{"estimated_diameter_min":15.0160247905,"estimated_diameter_max":33.5768521834}},"is_potentially_hazardous_asteroid":false,"close_approach_data":[{"close_approach_date":"2091-01-22","relative_velocity":{"kilometers_per_second":"20.3634675978"},"miss_distance":{"kilometers":"62694748"}}]}]