[{"name":"154993 (2005 EA94)","estimated_diameter":{"meters":{"estimated_diameter_min":667.6594134952,"estimated_diameter_max":1492.931834393}},"is_potentially_hazardous_asteroid":false,"close_approach_data":[{"close_approach_date":"1950-11-23","relative_velocity":{"kilometers_per_second":"23.9288652135"},"miss_distance":{"kilometers":"72322856"}}]},{"name":"(2001 VC2)","estimated_diameter":{"meters":{"estimated_diameter_min":152.9519353442,"estimated_diameter_max":342.0109247198}},"is_potentially_hazardous_asteroid":true,"close_approach_data":[{"close_approach_date":"1950-11-23","relative_velocity":{"kilometers_per_second":"6.6785798641"},"miss_distance":{"kilometers":"22702642"}}]},{"name":"(2011 EX4)","estimated_diameter":{"meters":{"estimated_diameter_min":31.9561886721,"estimated_diameter_max":71.4562101727}},"is_potentially_hazardous_asteroid":false,"close_approach_data":[{"close_approach_date":"1950-11-23","relative_velocity":{"kilometers_per_second":"9.4998424939"},"miss_distance":{"kilometers":"48414384"}}]}]