[{"name":"(2009 JR)","estimated_diameter":{"meters":{"estimated_diameter_min":139.4938229344,"estimated_diameter_max":311.9176705226}},"is_potentially_hazardous_asteroid":true,"close_approach_data":[{"close_approach_date":"1959-05-10","relative_velocity":{"kilometers_per_second":"17.4073017622"},"miss_distance":{"kilometers":"32090188"}}]},{"name":"(2010 RM80)","estimated_diameter":{"meters":{"estimated_diameter_min":6.9912523225,"estimated_diameter_max":15.6329154409}},"is_potentially_hazardous_asteroid":false,"close_approach_data":[{"close_approach_date":"1959-05-10","relative_velocity":{"kilometers_per_second":"4.8881812942"},"miss_distance":{"kilometers":"5667269.5"}}]},{"name":"(2014 TV)","estimated_diameter":{"meters":{"estimated_diameter_min":35.0392641108,"estimated_diameter_max":78.3501764334}},"is_potentially_hazardous_asteroid":false,"close_approach_data":[{"close_approach_date":"1959-05-10","relative_velocity":{"kilometers_per_second":"13.8073387743"},"miss_distance":{"kilometers":"12661774"}}]},{"name":"(2015 TM143)","estimated_diameter":{"meters":{"estimated_diameter_min":50.6471458835,"estimated_diameter_max":113.2504610618}},"is_potentially_hazardous_asteroid":false,"close_approach_data":[{"close_approach_date":"1959-05-10","relative_velocity":{"kilometers_per_second":"5.4846095422"},"miss_distance":{"kilometers":"40385552"}}]}]