[{"name":"(2010 MS1)","estimated_diameter":{"meters":{"estimated_diameter_min":116.0259082094,"estimated_diameter_max":259.4418179074}},"is_potentially_hazardous_asteroid":false,"close_approach_data":[{"close_approach_date":"1930-05-08","relative_velocity":{"kilometers_per_second":"21.1387309879"},"miss_distance":{"kilometers":"72117272"}}]},{"name":"(2012 FL35)","estimated_diameter":{"meters":{"estimated_diameter_min":305.1792325939,"estimated_diameter_max":682.4015094011}},"is_potentially_hazardous_asteroid":false,"close_approach_data":[{"close_approach_date":"1930-05-08","relative_velocity":{"kilometers_per_second":"18.0176131788"},"miss_distance":{"kilometers":"54408540"}}]},{"name":"(2014 TF64)","estimated_diameter":{"meters":{"estimated_diameter_min":253.8370293645,"estimated_diameter_max":567.5968528656}},"is_potentially_hazardous_asteroid":false,"close_approach_data":[{"close_approach_date":"1930-05-08","relative_velocity":{"kilometers_per_second":"27.3607732135"},"miss_distance":{"kilometers":"73667088"}}]}]