[{"name":"85990 (1999 JV6)","estimated_diameter":{"meters":{"estimated_diameter_min":242.4124811008,"estimated_diameter_max":542.0507863358}},"is_potentially_hazardous_asteroid":true,"close_approach_data":[{"close_approach_date":"2174-02-22","relative_velocity":{"kilometers_per_second":"8.1602488692"},"miss_distance":{"kilometers":"45265640"}}]},{"name":"(2007 DW)","estimated_diameter":{"meters":{"estimated_diameter_min":211.1324447897,"estimated_diameter_max":472.1064988055}},"is_potentially_hazardous_asteroid":false,"close_approach_data":[{"close_approach_date":"2174-02-22","relative_velocity":{"kilometers_per_second":"19.563225386"},"miss_distance":{"kilometers":"70944816"}}]},{"name":"(2013 UG1)","estimated_diameter":{"meters":{"estimated_diameter_min":88.0146520901,"estimated_diameter_max":196.8067450894}},"is_potentially_hazardous_asteroid":false,"close_approach_data":[{"close_approach_date":"2174-02-22","relative_velocity":{"kilometers_per_second":"9.8111635772"},"miss_distance":{"kilometers":"60898960"}}]}]