[{"name":"437844 (1999 MN)","estimated_diameter":{"meters":{"estimated_diameter_min":139.4938229344,"estimated_diameter_max":311.9176705226}},"is_potentially_hazardous_asteroid":true,"close_approach_data":[{"close_approach_date":"2020-06-25","relative_velocity":{"kilometers_per_second":"13.0925942929"},"miss_distance":{"kilometers":"15605792"}}]},{"name":"(2005 MN13)","estimated_diameter":{"meters":{"estimated_diameter_min":192.5550781879,"estimated_diameter_max":430.566244241}},"is_potentially_hazardous_asteroid":false,"close_approach_data":[{"close_approach_date":"2020-06-25","relative_velocity":{"kilometers_per_second":"12.3619064473"},"miss_distance":{"kilometers":"50374664"}}]},{"name":"(2006 XO4)","estimated_diameter":{"meters":{"estimated_diameter_min":55.5334911581,"estimated_diameter_max":124.1766612574}},"is_potentially_hazardous_asteroid":false,"close_approach_data":[{"close_approach_date":"2020-06-25","relative_velocity":{"kilometers_per_second":"15.2263484442"},"miss_distance":{"kilometers":"62866936"}}]},{"name":"(2017 FW128)","estimated_diameter":{"meters":{"estimated_diameter_min":8.9527194772,"estimated_diameter_max":20.0188893345}},"is_potentially_hazardous_asteroid":false,"close_approach_data":[{"close_approach_date":"2020-06-25","relative_velocity":{"kilometers_per_second":"5.4481407375"},"miss_distance":{"kilometers":"2626375.25"}}]}]