[{"name":"(2002 AY1)","estimated_diameter":{"meters":{"estimated_diameter_min":183.8886720703,"estimated_diameter_max":411.1875710413}},"is_potentially_hazardous_asteroid":true,"close_approach_data":[{"close_approach_date":"2066-01-05","relative_velocity":{"kilometers_per_second":"21.331616133"},"miss_distance":{"kilometers":"22271346"}}]},{"name":"(2008 QV11)","estimated_diameter":{"meters":{"estimated_diameter_min":167.7084621628,"estimated_diameter_max":375.0075217981}},"is_potentially_hazardous_asteroid":false,"close_approach_data":[{"close_approach_date":"2066-01-05","relative_velocity":{"kilometers_per_second":"20.7161388002"},"miss_distance":{"kilometers":"71690256"}}]},{"name":"(2016 QJ44)","estimated_diameter":{"meters":{"estimated_diameter_min":265.8,"estimated_diameter_max":594.3468684194}},"is_potentially_hazardous_asteroid":true,"close_approach_data":[{"close_approach_date":"2066-01-05","relative_velocity":{"kilometers_per_second":"8.2072564757"},"miss_distance":{"kilometers":"19922082"}}]}]