[{"name":"386259 (2008 EJ1)","estimated_diameter":{"meters":{"estimated_diameter_min":1925.5507818793,"estimated_diameter_max":4305.66244241}},"is_potentially_hazardous_asteroid":false,"close_approach_data":[{"close_approach_date":"2145-09-08","relative_velocity":{"kilometers_per_second":"24.0491181676"},"miss_distance":{"kilometers":"45019696"}}]},{"name":"(2011 GZ54)","estimated_diameter":{"meters":{"estimated_diameter_min":105.8168859331,"estimated_diameter_max":236.6137501138}},"is_potentially_hazardous_asteroid":false,"close_approach_data":[{"close_approach_date":"2145-09-08","relative_velocity":{"kilometers_per_second":"6.230344108"},"miss_distance":{"kilometers":"63274980"}}]},{"name":"(2011 KW15)","estimated_diameter":{"meters":{"estimated_diameter_min":350.3926411083,"estimated_diameter_max":783.5017643338}},"is_potentially_hazardous_asteroid":true,"close_approach_data":[{"close_approach_date":"2145-09-08","relative_velocity":{"kilometers_per_second":"15.1657897005"},"miss_distance":{"kilometers":"71298280"}}]},{"name":"471323 (2011 KW15)","estimated_diameter":{"meters":{"estimated_diameter_min":350.3926411083,"estimated_diameter_max":783.5017643338}},"is_potentially_hazardous_asteroid":true,"close_approach_data":[{"close_approach_date":"2145-09-08","relative_velocity":{"kilometers_per_second":"15.1657827915"},"miss_distance":{"kilometers":"71298256"}}]}]