[{"name":"11066 Sigurd (1992 CC1)","estimated_diameter":{"meters":{"estimated_diameter_min":2424.124811008,"estimated_diameter_max":5420.5078633577}},"is_potentially_hazardous_asteroid":false,"close_approach_data":[{"close_approach_date":"1963-08-31","relative_velocity":{"kilometers_per_second":"23.2920738035"},"miss_distance":{"kilometers":"28377570"}}]},{"name":"(1998 XN17)","estimated_diameter":{"meters":{"estimated_diameter_min":73.2073989347,"estimated_diameter_max":163.696720474}},"is_potentially_hazardous_asteroid":false,"close_approach_data":[{"close_approach_date":"1963-08-31","relative_velocity":{"kilometers_per_second":"7.409661703"},"miss_distance":{"kilometers":"36732516"}}]},{"name":"(2007 YZ)","estimated_diameter":{"meters":{"estimated_diameter_min":319.5618867213,"estimated_diameter_max":714.5621017269}},"is_potentially_hazardous_asteroid":false,"close_approach_data":[{"close_approach_date":"1963-08-31","relative_velocity":{"kilometers_per_second":"24.7209963473"},"miss_distance":{"kilometers":"70499960"}}]},{"name":"(2009 OP9)","estimated_diameter":{"meters":{"estimated_diameter_min":384.1978910643,"estimated_diameter_max":859.0926012318}},"is_potentially_hazardous_asteroid":false,"close_approach_data":[{"close_approach_date":"1963-08-31","relative_velocity":{"kilometers_per_second":"9.7451231416"},"miss_distance":{"kilometers":"16492493"}}]}]