[{"name":"426071 (2012 CD29)","estimated_diameter":{"meters":{"estimated_diameter_min":265.8,"estimated_diameter_max":594.3468684194}},"is_potentially_hazardous_asteroid":false,"close_approach_data":[{"close_approach_date":"2041-02-26","relative_velocity":{"kilometers_per_second":"16.2918453515"},"miss_distance":{"kilometers":"65669000"}}]},{"name":"(2016 GA3)","estimated_diameter":{"meters":{"estimated_diameter_min":29.1443904535,"estimated_diameter_max":65.1688382168}},"is_potentially_hazardous_asteroid":false,"close_approach_data":[{"close_approach_date":"2041-02-26","relative_velocity":{"kilometers_per_second":"5.8659947986"},"miss_distance":{"kilometers":"29582906"}}]},{"name":"(2017 XS2)","estimated_diameter":{"meters":{"estimated_diameter_min":16.8637818917,"estimated_diameter_max":37.7085626676}},"is_potentially_hazardous_asteroid":false,"close_approach_data":[{"close_approach_date":"2041-02-26","relative_velocity":{"kilometers_per_second":"19.208137781"},"miss_distance":{"kilometers":"68933128"}}]}]