[{"name":"(2001 BB16)","estimated_diameter":{"meters":{"estimated_diameter_min":60.8912622106,"estimated_diameter_max":136.1570015386}},"is_potentially_hazardous_asteroid":false,"close_approach_data":[{"close_approach_date":"2146-08-03","relative_velocity":{"kilometers_per_second":"8.7733217552"},"miss_distance":{"kilometers":"44806792"}}]},{"name":"(2015 JJ2)","estimated_diameter":{"meters":{"estimated_diameter_min":110.8038821264,"estimated_diameter_max":247.7650126055}},"is_potentially_hazardous_asteroid":false,"close_approach_data":[{"close_approach_date":"2146-08-03","relative_velocity":{"kilometers_per_second":"6.8449277715"},"miss_distance":{"kilometers":"17214444"}}]},{"name":"(2016 PS)","estimated_diameter":{"meters":{"estimated_diameter_min":46.1907460282,"estimated_diameter_max":103.2856480504}},"is_potentially_hazardous_asteroid":false,"close_approach_data":[{"close_approach_date":"2146-08-03","relative_velocity":{"kilometers_per_second":"5.1704269139"},"miss_distance":{"kilometers":"27674942"}}]}]