[{"name":"(2002 XB)","estimated_diameter":{"meters":{"estimated_diameter_min":116.0259082094,"estimated_diameter_max":259.4418179074}},"is_potentially_hazardous_asteroid":false,"close_approach_data":[{"close_approach_date":"2170-06-02","relative_velocity":{"kilometers_per_second":"18.308517869"},"miss_distance":{"kilometers":"47954784"}}]},{"name":"(2006 SY5)","estimated_diameter":{"meters":{"estimated_diameter_min":101.054341542,"estimated_diameter_max":225.9643771094}},"is_potentially_hazardous_asteroid":false,"close_approach_data":[{"close_approach_date":"2170-06-02","relative_velocity":{"kilometers_per_second":"10.9682756267"},"miss_distance":{"kilometers":"40008016"}}]}]