[{"name":"(2003 MK4)","estimated_diameter":{"meters":{"estimated_diameter_min":175.6123184804,"estimated_diameter_max":392.6810818086}},"is_potentially_hazardous_asteroid":true,"close_approach_data":[{"close_approach_date":"1985-12-24","relative_velocity":{"kilometers_per_second":"12.2230013533"},"miss_distance":{"kilometers":"41386048"}}]},{"name":"(1993 KA)","estimated_diameter":{"meters":{"estimated_diameter_min":16.7708462163,"estimated_diameter_max":37.5007521798}},"is_potentially_hazardous_asteroid":false,"close_approach_data":[{"close_approach_date":"1985-12-24","relative_velocity":{"kilometers_per_second":"6.7242892916"},"miss_distance":{"kilometers":"58032132"}}]},{"name":"(2012 YK)","estimated_diameter":{"meters":{"estimated_diameter_min":66.7659413495,"estimated_diameter_max":149.2931834393}},"is_potentially_hazardous_asteroid":false,"close_approach_data":[{"close_approach_date":"1985-12-24","relative_velocity":{"kilometers_per_second":"23.406131451"},"miss_distance":{"kilometers":"63686916"}}]},{"name":"(2017 WJ16)","estimated_diameter":{"meters":{"estimated_diameter_min":36.7582626492,"estimated_diameter_max":82.1939740183}},"is_potentially_hazardous_asteroid":false,"close_approach_data":[{"close_approach_date":"1985-12-24","relative_velocity":{"kilometers_per_second":"11.6059593983"},"miss_distance":{"kilometers":"34535476"}}]}]