[{"name":"5381 Sekhmet (1991 JY)","estimated_diameter":{"meters":{"estimated_diameter_min":1272.1987853936,"estimated_diameter_max":2844.7229650327}},"is_potentially_hazardous_asteroid":false,"close_approach_data":[{"close_approach_date":"1990-05-26","relative_velocity":{"kilometers_per_second":"29.0407654731"},"miss_distance":{"kilometers":"59894800"}}]},{"name":"(2005 WR2)","estimated_diameter":{"meters":{"estimated_diameter_min":366.9061375314,"estimated_diameter_max":820.4270648822}},"is_potentially_hazardous_asteroid":false,"close_approach_data":[{"close_approach_date":"1990-05-26","relative_velocity":{"kilometers_per_second":"18.7031610064"},"miss_distance":{"kilometers":"17184972"}}]}]